Metadata-Version: 1.0
Name: advimport
Version: 0.7.1
Summary: Better and easier imports
Home-page: https://github.com/davix3f/advimport
Author: davix3f
Author-email: davide_fiorito@libero.it
License: GNU GPL v3
Platform: UNKNOWN
